priority_queue/priority_queue.srcs/sources_1/new/queue.v
`timescale 1ns / 1ps
//////////////////////////////////////////////////////////////////////////////////
// Company: 
// Engineer: 
// 
// Create Date: 05/10/2023 01:07:05 PM
// Design Name: 
// Module Name: queue
// Project Name: 
// Target Devices: 
// Tool Versions: 
// Description: 
// 
// Dependencies: 
// 
// Revision:
// Revision 0.01 - File Created
// Additional Comments:
// 
//////////////////////////////////////////////////////////////////////////////////


module queue(
    output reg [15:0] dout,
    input [15:0] din,
    input en,
    input wr_en,
    input clk
    );
    parameter reg_depth = 2000 ;
    reg [15:0] reg_bank [reg_depth:0];
    integer i;
    always @(posedge clk) begin
        if(en && wr_en) begin
            
            if(din <= reg_bank[0] || reg_bank[0] === 16'hxxxx) begin
                $display("true");
                reg_bank[0] <= din;
            end
            for(i = 1; i<=reg_depth; i = i+1) begin
                if(din <= reg_bank[i] || reg_bank[i] === 16'hxxxx) begin
                    if(din <= reg_bank[i-1] || reg_bank[i-1] === 16'hxxxx)
                        reg_bank[i] <= reg_bank[i-1];
                    else
                        reg_bank[i] <= din;
                end
            end
        end
        else if( en && !wr_en) begin
            dout  <= reg_bank[0];
            for(i = 0; i<reg_depth; i = i+1)
                reg_bank[i] <= reg_bank[i+1];
            reg_bank[reg_depth] <= 16'hxxxx;
        end
    end
    
endmodule

priority_queue/priority_queue.srcs/sim_1/new/queue_tb.v
`timescale 1ns / 1ps
//////////////////////////////////////////////////////////////////////////////////
// Company: 
// Engineer: 
// 
// Create Date: 05/10/2023 01:18:47 PM
// Design Name: 
// Module Name: queue_tb
// Project Name: 
// Target Devices: 
// Tool Versions: 
// Description: 
// 
// Dependencies: 
// 
// Revision:
// Revision 0.01 - File Created
// Additional Comments:
// 
//////////////////////////////////////////////////////////////////////////////////


module queue_tb;
    reg clk, en, wr_en;
    reg[15:0] din;
    wire[15:0] dout;
    
    queue dut(.clk(clk), .en(en), .wr_en(wr_en), .din(din), .dout(dout));
    
    initial clk = 0;
    
    always #5 clk = ~clk;
    
    initial begin
        $dumpvars(1, queue_tb);
        #3 en = 1'b1; wr_en = 1'b1; din <= 16'hffff;
        #10 din <= 16'h0010;
        #10 din <= 16'h0003;
        #10 din <= 16'h000A;
        #10 din <= 16'h0011;
        #10 din <= 16'h000D;
        #10 din <= 16'h010A;
        #10 din <= 16'h0011;
        #10 din <= 16'h0100;
        #10 wr_en = 1'b0;
        #40 din = 16'h0010;wr_en = 1'b1; 
        #10 en = 1'b0;
        #10 $finish;
    end
    
endmodule

priority_queue/priority_queue.sim/sim_1/behav/xsim/dump.vcd
$date
   Wed May 10 22:03:13 2023
$end
$version
  2022.2
$end
$timescale
  1ps
$end
$scope module queue_tb $end
$var reg 1 ! clk $end
$var reg 1 " en $end
$var reg 1 # wr_en $end
$var reg 16 $ din [15:0] $end
$var wire 16 % dout [15:0] $end
$upscope $end
$enddefinitions $end
#0
$dumpvars
0!
x"
x#
bx $
bx %
$end
#3000
1"
1#
b1111111111111111 $
#5000
1!
#10000
0!
#13000
b10000 $
#15000
1!
#20000
0!
#23000
b11 $
#25000
1!
#30000
0!
#33000
b1010 $
#35000
1!
#40000
0!
#43000
b10001 $
#45000
1!
#50000
0!
#53000
b1101 $
#55000
1!
#60000
0!
#63000
b100001010 $
#65000
1!
#70000
0!
#73000
b10001 $
#75000
1!
#80000
0!
#83000
b100000000 $
#85000
1!
#90000
0!
#93000
0#
#95000
1!
b11 %
#100000
0!
#105000
1!
b1010 %
#110000
0!
#115000
1!
b1101 %
#120000
0!
#125000
1!
b10000 %
#130000
0!
#133000
1#
b10000 $
#135000
1!
#140000
0!
#143000
0"
