priority_queue/priority_queue.srcs/sources_1/new/queue.v
`timescale 1ns / 1ps
//////////////////////////////////////////////////////////////////////////////////
// Company: 
// Engineer: 
// 
// Create Date: 05/10/2023 01:07:05 PM
// Design Name: 
// Module Name: queue
// Project Name: 
// Target Devices: 
// Tool Versions: 
// Description: 
// 
// Dependencies: 
// 
// Revision:
// Revision 0.01 - File Created
// Additional Comments:
// 
//////////////////////////////////////////////////////////////////////////////////


module queue #(parameter data_width = 83)(
    output reg [data_width-1:0] dout,
    input [data_width-1:0] din,
    input en,
    input wr_en,
    input clk
    );
    parameter reg_depth = 100 ;
    reg [data_width-1:0] reg_bank [reg_depth:0];
    integer i;
    always @(posedge clk) begin
        if(en && wr_en) begin
            
            if(din <= reg_bank[0] || reg_bank[0] === 83'bxxxx) begin
                $display("true");
                reg_bank[0] <= din;
            end
            for(i = 1; i<=reg_depth; i = i+1) begin
                if(din[82:51] <= reg_bank[i][82:51] || reg_bank[i][82:51] === 32'bxxxx) begin
                    if(din[82:51] <= reg_bank[i-1][82:51] || reg_bank[i-1][82:51] === 32'bxxxx)
                        reg_bank[i] <= reg_bank[i-1];
                    else
                        reg_bank[i] <= din;
                end
            end
        end
        else if( en && !wr_en) begin
            for(i = 0; i<reg_depth; i = i+1)
                reg_bank[i] <= reg_bank[i+1];
            reg_bank[reg_depth] <= 83'bxxxx;
        end
       dout  <= reg_bank[0]; 
    end
    
endmodule

current_node_evaluator/current_node_evaluator.srcs/sim_1/new/queue_tb.v
`timescale 1ns / 1ps
//////////////////////////////////////////////////////////////////////////////////
// Company: 
// Engineer: 
// 
// Create Date: 05/10/2023 01:18:47 PM
// Design Name: 
// Module Name: queue_tb
// Project Name: 
// Target Devices: 
// Tool Versions: 
// Description: 
// 
// Dependencies: 
// 
// Revision:
// Revision 0.01 - File Created
// Additional Comments:
// 
//////////////////////////////////////////////////////////////////////////////////


module queue_tb;
    reg clk, en, wr_en;
    reg[82:0] din;
    wire[82:0] dout;
    
    queue #(.data_width(83)) dut(.clk(clk), .en(en), .wr_en(wr_en), .din(din), .dout(dout));
    
    initial clk = 0;
    
    always #5 clk = ~clk;
    
    initial begin
        $dumpvars(1, queue_tb);
        #3 en = 1'b1; wr_en = 1'b1; din <= 83'h01010001111011110001101100101110101001000111111100001100111101100011011100101101110;
        #10 din <= 83'b00110011111011111100111010011000101010011100100001100000010101100111000100110010100;
        #10 din <= 83'b01001010001110100010100011101000111001000110000111100110100011010000100111111011001;
        #10 din <= 83'b10000100011000000101011011100000001101110101000101010011100000000110110101001110001;
        #10 din <= 83'b00000100011101111111011001011110000011010001110111001011011000011000011110100100011;
        #10 din <= 83'b01100101110111011001101000001011100110010010101011001001111100011100100101010011010;
        #10 din <= 83'b01010110100101110111001110011011011000101110000110100000011001011011100111011110110;
        #10 din <= 83'b11000111000101011010010100011111000010001010110100011011111001100111110000010110001;
        #10 din <= 83'b10111001110000011101001110010011011011100001111011010000001100111010100100101010110;
        #10 wr_en = 1'b0;
        #40 din = 83'b00010111110000010010000110110011000001111111101011000000010001001100000111000011000;wr_en = 1'b1; 
        #10 en = 1'b0;
        #10 $finish;
    end
    
endmodule

priority_queue/priority_queue.sim/sim_1/behav/xsim/dump.vcd
$date
   Sun May 21 17:11:52 2023
$end
$version
  2022.2
$end
$timescale
  1ps
$end
$scope module queue_tb $end
$var reg 1 ! clk $end
$var reg 1 " en $end
$var reg 1 # wr_en $end
$var reg 83 $ din [82:0] $end
$var wire 83 % dout [82:0] $end
$upscope $end
$enddefinitions $end
#0
$dumpvars
0!
x"
x#
bx $
bx %
$end
#3000
1"
1#
b100000000000000010001000000010001000100000000000100000001000100000001000100010000 $
#5000
1!
#10000
0!
#13000
b110011111011111100111010011000101010011100100001100000010101100111000100110010100 $
#15000
1!
b100000000000000010001000000010001000100000000000100000001000100000001000100010000 %
#20000
0!
#23000
b1001010001110100010100011101000111001000110000111100110100011010000100111111011001 $
#25000
1!
#30000
0!
#33000
b10000100011000000101011011100000001101110101000101010011100000000110110101001110001 $
#35000
1!
#40000
0!
#43000
b100011101111111011001011110000011010001110111001011011000011000011110100100011 $
#45000
1!
#50000
0!
#53000
b1100101110111011001101000001011100110010010101011001001111100011100100101010011010 $
#55000
1!
b100011101111111011001011110000011010001110111001011011000011000011110100100011 %
#60000
0!
#63000
b1010110100101110111001110011011011000101110000110100000011001011011100111011110110 $
#65000
1!
#70000
0!
#73000
b11000111000101011010010100011111000010001010110100011011111001100111110000010110001 $
#75000
1!
#80000
0!
#83000
b10111001110000011101001110010011011011100001111011010000001100111010100100101010110 $
#85000
1!
#90000
0!
#93000
0#
#95000
1!
#100000
0!
#105000
1!
b100000000000000010001000000010001000100000000000100000001000100000001000100010000 %
#110000
0!
#115000
1!
b110011111011111100111010011000101010011100100001100000010101100111000100110010100 %
#120000
0!
#125000
1!
b1001010001110100010100011101000111001000110000111100110100011010000100111111011001 %
#130000
0!
#133000
1#
b10111110000010010000110110011000001111111101011000000010001001100000111000011000 $
#135000
1!
b1010110100101110111001110011011011000101110000110100000011001011011100111011110110 %
#140000
0!
#143000
0"
#145000
1!
b10111110000010010000110110011000001111111101011000000010001001100000111000011000 %
