memory_manager/memory_manager.srcs/sources_1/new/control_path.v
`timescale 1ns / 1ps
//////////////////////////////////////////////////////////////////////////////////
// Company: 
// Engineer: 
//
// Create Date: 04/07/2023 02:05:19 PM
// Design Name: 
// Module Name: control_path
// Project Name: 
// Target Devices: 
// Tool Versions: 
// Description: 
// 
// Dependencies: 
// 
// Revision:
// Revision 0.01 - File Created
// Additional Comments:
// 
//////////////////////////////////////////////////////////////////////////////////


module control_path(
    input clk,
    input enable,
//    input [34:0] current,
//    output reg [127:0] data,
    output reg ready   
    );
    parameter a = 3'b000, b = 3'b001, c = 3'b010 , d = 3'b011, e = 3'b100;
    reg [50:0] current_reg;
    reg current_reg_en, piso_wr_en, piso_rd_en, sipo_en, bram_en;
    reg sipo_overflow, current_reg_overflow, bram_write_ack, piso_overflow, sipo_empty;
    reg [2:0] state;
    always @(posedge clk) 
    begin
        case (state)
        a: if(enable) state <= b;
        b: if(current_reg_overflow) state <= c;
        c: if(piso_overflow) state <= d;
        d: if(sipo_overflow) state <= e;
        e: if(sipo_empty) state <= a;
        default: state <= a;
        endcase
    end
    
    always @(state)
    begin 
        case(state)
        a:;
        b: current_reg_en <= 1'b1;
        c: begin 
            piso_wr_en<= 1'b1; current_reg_en <= 1'b0; 
           end
        d: begin 
            piso_wr_en<= 1'b0; piso_rd_en<= 1'b1; sipo_en <= 1'b1; bram_en <= 1'b1;
           end
        e: begin
            ready <= 1'b1;
           end
        endcase
    end
endmodule

memory_manager/memory_manager.srcs/sim_1/new/control_path_tb.v
`timescale 1ns / 1ps
//////////////////////////////////////////////////////////////////////////////////
// Company: 
// Engineer: 
// 
// Create Date: 04/23/2023 12:12:59 PM
// Design Name: 
// Module Name: control_path_tb
// Project Name: 
// Target Devices: 
// Tool Versions: 
// Description: 
// 
// Dependencies: 
// 
// Revision:
// Revision 0.01 - File Created
// Additional Comments:
// 
//////////////////////////////////////////////////////////////////////////////////


module control_path_tb(
    );
    reg clk, enable;
    wire ready;
    control_path dut(.clk(clk), .enable(enable), .ready(ready));
    initial clk = 1'b0;
    always #5 clk = ~clk;
    initial
    begin
        $dumpvars(0, control_path_tb);
        #13 enable = 1'b1;
        #10 dut.current_reg_overflow = 1'b1; enable = 1'b0;
        #10 dut.piso_overflow = 1'b1; dut.current_reg_overflow = 1'b0;
        #10 dut.sipo_overflow = 1'b1;dut.piso_overflow = 1'b0;
        #10 dut.sipo_empty = 1'b1; dut.sipo_overflow = 1'b0;
        #10 dut.sipo_empty = 1'b0;
        #70 $finish;
    end
endmodule

memory_manager/memory_manager.sim/sim_1/behav/xsim/dump.vcd
$date
   Sun Apr 23 19:47:44 2023
$end
$version
  2022.2
$end
$timescale
  1ps
$end
$scope module control_path_tb $end
$var reg 1 ! clk $end
$var reg 1 " enable $end
$var wire 1 # ready $end
$scope module dut $end
$var wire 1 $ clk $end
$var wire 1 % enable $end
$var reg 1 & ready $end
$var reg 51 ' current_reg [50:0] $end
$var reg 1 ( current_reg_en $end
$var reg 1 ) piso_wr_en $end
$var reg 1 * piso_rd_en $end
$var reg 1 + sipo_en $end
$var reg 1 , bram_en $end
$var reg 1 - sipo_overflow $end
$var reg 1 . current_reg_overflow $end
$var reg 1 / bram_write_ack $end
$var reg 1 0 piso_overflow $end
$var reg 1 1 sipo_empty $end
$var reg 3 2 state [2:0] $end
$upscope $end
$upscope $end
$enddefinitions $end
#0
$dumpvars
0!
x"
x#
0$
x%
x&
bx '
x(
x)
x*
x+
x,
x-
x.
x/
x0
x1
bx 2
$end
#5000
1!
1$
b0 2
#10000
0!
0$
#13000
1"
1%
#15000
1!
1$
1(
b1 2
#20000
0!
0$
#23000
0"
0%
1.
#25000
1!
1$
0(
1)
b10 2
#30000
0!
0$
#33000
0.
10
#35000
1!
1$
0)
1*
1+
1,
b11 2
#40000
0!
0$
#43000
1-
00
#45000
1!
1#
1$
1&
b100 2
#50000
0!
0$
#53000
0-
11
#55000
1!
1$
b0 2
#60000
0!
0$
#63000
01
